token_env/__init__.py
token_env/token_env.py
token_env-0.2.2.dist-info/METADATA
token_env-0.2.2.dist-info/WHEEL
token_env-0.2.2.dist-info/licenses/LICENSE
token_env-0.2.2.dist-info/RECORD
