Metadata-Version: 2.4
Name: token-env
Version: 0.2.2
Summary: Gymnasium grid environment with random tokens
License-File: LICENSE
Requires-Python: >=3.12
Requires-Dist: gymnasium>=1.0.0
Requires-Dist: numpy>=1.20
